{
  "format_version": "1.12",
  "minecraft:recipe_shaped": {
    "description": {
      "identifier": "alkahestry_tome8_jytre6fy"
    },
    "tags": [ "crafting_table" ],
    "pattern": [
      "AB"
    ],
    "key": {
      "A": {
        "item": "minecraft:netherrack",
        "data": 0
      },
      "B": {
        "item": "bg:alkahestry_tome8",
        "data": 0
      }
    },
    "result":[
      {
      "item":"minecraft:netherrack",
      "count": 9
      },
      {
      "item":"bg:alkahestry_tome4",
      "count": 1
      }
    ]
  }
}
