{
  "format_version": "1.12",
  "minecraft:recipe_shaped": {
    "description": {
      "identifier": "alkahestry_tome256_he3yhycj"
    },
    "tags": [ "crafting_table" ],
    "pattern": [
      "AB"
    ],
    "key": {
      "A": {
        "item": "minecraft:gold_ingot",
        "data": 0
      },
      "B": {
        "item": "bg:alkahestry_tome256",
        "data": 0
      }
    },
    "result":[
      {
      "item":"minecraft:gold_ingot",
      "count": 7
      },
      {
      "item":"bg:alkahestry_tome64",
      "count": 1
      }
    ]
  }
}
